{"metadata": {"dbt_schema_version": "https://schemas.getdbt.com/dbt/run-results/v4.json", "dbt_version": "1.0.0", "generated_at": "2021-12-31T19:20:17.727464Z", "invocation_id": "a77cc5f3-b295-4205-8a59-395333319c20", "env": {}}, "results": [{"status": "success", "timing": [{"name": "compile", "started_at": "2021-12-31T19:20:17.620463Z", "completed_at": "2021-12-31T19:20:17.621464Z"}, {"name": "execute", "started_at": "2021-12-31T19:20:17.621464Z", "completed_at": "2021-12-31T19:20:17.621464Z"}], "thread_id": "Thread-1", "execution_time": 0.0020024776458740234, "adapter_response": {}, "message": null, "failures": null, "unique_id": "seed.sampledatastack.raw_customers"}, {"status": "success", "timing": [{"name": "compile", "started_at": "2021-12-31T19:20:17.622460Z", "completed_at": "2021-12-31T19:20:17.623464Z"}, {"name": "execute", "started_at": "2021-12-31T19:20:17.623464Z", "completed_at": "2021-12-31T19:20:17.623464Z"}], "thread_id": "Thread-1", "execution_time": 0.0010037422180175781, "adapter_response": {}, "message": null, "failures": null, "unique_id": "seed.sampledatastack.raw_orders"}, {"status": "success", "timing": [{"name": "compile", "started_at": "2021-12-31T19:20:17.624462Z", "completed_at": "2021-12-31T19:20:17.625464Z"}, {"name": "execute", "started_at": "2021-12-31T19:20:17.626465Z", "completed_at": "2021-12-31T19:20:17.626465Z"}], "thread_id": "Thread-1", "execution_time": 0.002003192901611328, "adapter_response": {}, "message": null, "failures": null, "unique_id": "seed.sampledatastack.raw_payments"}, {"status": "success", "timing": [{"name": "compile", "started_at": "2021-12-31T19:20:17.627462Z", "completed_at": "2021-12-31T19:20:17.629464Z"}, {"name": "execute", "started_at": "2021-12-31T19:20:17.629464Z", "completed_at": "2021-12-31T19:20:17.630461Z"}], "thread_id": "Thread-1", "execution_time": 0.0039958953857421875, "adapter_response": {}, "message": null, "failures": null, "unique_id": "model.sampledatastack.stg_customers"}, {"status": "success", "timing": [{"name": "compile", "started_at": "2021-12-31T19:20:17.631461Z", "completed_at": "2021-12-31T19:20:17.634464Z"}, {"name": "execute", "started_at": "2021-12-31T19:20:17.634464Z", "completed_at": "2021-12-31T19:20:17.634464Z"}], "thread_id": "Thread-1", "execution_time": 0.003002643585205078, "adapter_response": {}, "message": null, "failures": null, "unique_id": "model.sampledatastack.stg_orders"}, {"status": "success", "timing": [{"name": "compile", "started_at": "2021-12-31T19:20:17.635463Z", "completed_at": "2021-12-31T19:20:17.637461Z"}, {"name": "execute", "started_at": "2021-12-31T19:20:17.637461Z", "completed_at": "2021-12-31T19:20:17.637461Z"}], "thread_id": "Thread-1", "execution_time": 0.0029964447021484375, "adapter_response": {}, "message": null, "failures": null, "unique_id": "model.sampledatastack.stg_payments"}, {"status": "success", "timing": [{"name": "compile", "started_at": "2021-12-31T19:20:17.638460Z", "completed_at": "2021-12-31T19:20:17.643464Z"}, {"name": "execute", "started_at": "2021-12-31T19:20:17.644460Z", "completed_at": "2021-12-31T19:20:17.644460Z"}], "thread_id": "Thread-1", "execution_time": 0.006000518798828125, "adapter_response": {}, "message": null, "failures": null, "unique_id": "test.sampledatastack.not_null_stg_customers_customer_id.e2cfb1f9aa"}, {"status": "success", "timing": [{"name": "compile", "started_at": "2021-12-31T19:20:17.645460Z", "completed_at": "2021-12-31T19:20:17.649463Z"}, {"name": "execute", "started_at": "2021-12-31T19:20:17.649463Z", "completed_at": "2021-12-31T19:20:17.649463Z"}], "thread_id": "Thread-1", "execution_time": 0.00599980354309082, "adapter_response": {}, "message": null, "failures": null, "unique_id": "test.sampledatastack.unique_stg_customers_customer_id.c7614daada"}, {"status": "success", "timing": [{"name": "compile", "started_at": "2021-12-31T19:20:17.650460Z", "completed_at": "2021-12-31T19:20:17.654460Z"}, {"name": "execute", "started_at": "2021-12-31T19:20:17.654460Z", "completed_at": "2021-12-31T19:20:17.654460Z"}], "thread_id": "Thread-1", "execution_time": 0.005001544952392578, "adapter_response": {}, "message": null, "failures": null, "unique_id": "test.sampledatastack.accepted_values_stg_orders_status__placed__shipped__completed__return_pending__returned.080fb20aad"}, {"status": "success", "timing": [{"name": "compile", "started_at": "2021-12-31T19:20:17.655461Z", "completed_at": "2021-12-31T19:20:17.658462Z"}, {"name": "execute", "started_at": "2021-12-31T19:20:17.659529Z", "completed_at": "2021-12-31T19:20:17.659529Z"}], "thread_id": "Thread-1", "execution_time": 0.004067182540893555, "adapter_response": {}, "message": null, "failures": null, "unique_id": "test.sampledatastack.not_null_stg_orders_order_id.81cfe2fe64"}, {"status": "success", "timing": [{"name": "compile", "started_at": "2021-12-31T19:20:17.660463Z", "completed_at": "2021-12-31T19:20:17.662464Z"}, {"name": "execute", "started_at": "2021-12-31T19:20:17.663464Z", "completed_at": "2021-12-31T19:20:17.663464Z"}], "thread_id": "Thread-1", "execution_time": 0.003936052322387695, "adapter_response": {}, "message": null, "failures": null, "unique_id": "test.sampledatastack.unique_stg_orders_order_id.e3b841c71a"}, {"status": "success", "timing": [{"name": "compile", "started_at": "2021-12-31T19:20:17.663464Z", "completed_at": "2021-12-31T19:20:17.666463Z"}, {"name": "execute", "started_at": "2021-12-31T19:20:17.666463Z", "completed_at": "2021-12-31T19:20:17.666463Z"}], "thread_id": "Thread-1", "execution_time": 0.0029990673065185547, "adapter_response": {}, "message": null, "failures": null, "unique_id": "model.sampledatastack.customers"}, {"status": "success", "timing": [{"name": "compile", "started_at": "2021-12-31T19:20:17.667464Z", "completed_at": "2021-12-31T19:20:17.670464Z"}, {"name": "execute", "started_at": "2021-12-31T19:20:17.670464Z", "completed_at": "2021-12-31T19:20:17.670464Z"}], "thread_id": "Thread-1", "execution_time": 0.003999948501586914, "adapter_response": {}, "message": null, "failures": null, "unique_id": "model.sampledatastack.orders"}, {"status": "success", "timing": [{"name": "compile", "started_at": "2021-12-31T19:20:17.671464Z", "completed_at": "2021-12-31T19:20:17.675464Z"}, {"name": "execute", "started_at": "2021-12-31T19:20:17.675464Z", "completed_at": "2021-12-31T19:20:17.675464Z"}], "thread_id": "Thread-1", "execution_time": 0.0039997100830078125, "adapter_response": {}, "message": null, "failures": null, "unique_id": "test.sampledatastack.accepted_values_stg_payments_payment_method__credit_card__coupon__bank_transfer__gift_card.3c3820f278"}, {"status": "success", "timing": [{"name": "compile", "started_at": "2021-12-31T19:20:17.676465Z", "completed_at": "2021-12-31T19:20:17.678464Z"}, {"name": "execute", "started_at": "2021-12-31T19:20:17.679465Z", "completed_at": "2021-12-31T19:20:17.679465Z"}], "thread_id": "Thread-1", "execution_time": 0.0030002593994140625, "adapter_response": {}, "message": null, "failures": null, "unique_id": "test.sampledatastack.not_null_stg_payments_payment_id.c19cc50075"}, {"status": "success", "timing": [{"name": "compile", "started_at": "2021-12-31T19:20:17.679465Z", "completed_at": "2021-12-31T19:20:17.682464Z"}, {"name": "execute", "started_at": "2021-12-31T19:20:17.682464Z", "completed_at": "2021-12-31T19:20:17.682464Z"}], "thread_id": "Thread-1", "execution_time": 0.0029990673065185547, "adapter_response": {}, "message": null, "failures": null, "unique_id": "test.sampledatastack.unique_stg_payments_payment_id.3744510712"}, {"status": "success", "timing": [{"name": "compile", "started_at": "2021-12-31T19:20:17.683463Z", "completed_at": "2021-12-31T19:20:17.686464Z"}, {"name": "execute", "started_at": "2021-12-31T19:20:17.686464Z", "completed_at": "2021-12-31T19:20:17.686464Z"}], "thread_id": "Thread-1", "execution_time": 0.003999948501586914, "adapter_response": {}, "message": null, "failures": null, "unique_id": "test.sampledatastack.not_null_customers_customer_id.5c9bf9911d"}, {"status": "success", "timing": [{"name": "compile", "started_at": "2021-12-31T19:20:17.687465Z", "completed_at": "2021-12-31T19:20:17.689464Z"}, {"name": "execute", "started_at": "2021-12-31T19:20:17.689464Z", "completed_at": "2021-12-31T19:20:17.689464Z"}], "thread_id": "Thread-1", "execution_time": 0.0030002593994140625, "adapter_response": {}, "message": null, "failures": null, "unique_id": "test.sampledatastack.unique_customers_customer_id.c5af1ff4b1"}, {"status": "success", "timing": [{"name": "compile", "started_at": "2021-12-31T19:20:17.690465Z", "completed_at": "2021-12-31T19:20:17.694464Z"}, {"name": "execute", "started_at": "2021-12-31T19:20:17.694464Z", "completed_at": "2021-12-31T19:20:17.694464Z"}], "thread_id": "Thread-1", "execution_time": 0.004999399185180664, "adapter_response": {}, "message": null, "failures": null, "unique_id": "test.sampledatastack.accepted_values_orders_status__placed__shipped__completed__return_pending__returned.be6b5b5ec3"}, {"status": "success", "timing": [{"name": "compile", "started_at": "2021-12-31T19:20:17.695464Z", "completed_at": "2021-12-31T19:20:17.697464Z"}, {"name": "execute", "started_at": "2021-12-31T19:20:17.698465Z", "completed_at": "2021-12-31T19:20:17.698465Z"}], "thread_id": "Thread-1", "execution_time": 0.0030007362365722656, "adapter_response": {}, "message": null, "failures": null, "unique_id": "test.sampledatastack.not_null_orders_amount.106140f9fd"}, {"status": "success", "timing": [{"name": "compile", "started_at": "2021-12-31T19:20:17.698465Z", "completed_at": "2021-12-31T19:20:17.701464Z"}, {"name": "execute", "started_at": "2021-12-31T19:20:17.701464Z", "completed_at": "2021-12-31T19:20:17.701464Z"}], "thread_id": "Thread-1", "execution_time": 0.0029990673065185547, "adapter_response": {}, "message": null, "failures": null, "unique_id": "test.sampledatastack.not_null_orders_bank_transfer_amount.7743500c49"}, {"status": "success", "timing": [{"name": "compile", "started_at": "2021-12-31T19:20:17.702464Z", "completed_at": "2021-12-31T19:20:17.704464Z"}, {"name": "execute", "started_at": "2021-12-31T19:20:17.705465Z", "completed_at": "2021-12-31T19:20:17.705465Z"}], "thread_id": "Thread-1", "execution_time": 0.0030002593994140625, "adapter_response": {}, "message": null, "failures": null, "unique_id": "test.sampledatastack.not_null_orders_coupon_amount.ab90c90625"}, {"status": "success", "timing": [{"name": "compile", "started_at": "2021-12-31T19:20:17.706464Z", "completed_at": "2021-12-31T19:20:17.708464Z"}, {"name": "execute", "started_at": "2021-12-31T19:20:17.708464Z", "completed_at": "2021-12-31T19:20:17.708464Z"}], "thread_id": "Thread-1", "execution_time": 0.0029993057250976562, "adapter_response": {}, "message": null, "failures": null, "unique_id": "test.sampledatastack.not_null_orders_credit_card_amount.d3ca593b59"}, {"status": "success", "timing": [{"name": "compile", "started_at": "2021-12-31T19:20:17.709464Z", "completed_at": "2021-12-31T19:20:17.712464Z"}, {"name": "execute", "started_at": "2021-12-31T19:20:17.712464Z", "completed_at": "2021-12-31T19:20:17.712464Z"}], "thread_id": "Thread-1", "execution_time": 0.002999544143676758, "adapter_response": {}, "message": null, "failures": null, "unique_id": "test.sampledatastack.not_null_orders_customer_id.c5f02694af"}, {"status": "success", "timing": [{"name": "compile", "started_at": "2021-12-31T19:20:17.713464Z", "completed_at": "2021-12-31T19:20:17.715464Z"}, {"name": "execute", "started_at": "2021-12-31T19:20:17.715464Z", "completed_at": "2021-12-31T19:20:17.715464Z"}], "thread_id": "Thread-1", "execution_time": 0.0029997825622558594, "adapter_response": {}, "message": null, "failures": null, "unique_id": "test.sampledatastack.not_null_orders_gift_card_amount.413a0d2d7a"}, {"status": "success", "timing": [{"name": "compile", "started_at": "2021-12-31T19:20:17.716465Z", "completed_at": "2021-12-31T19:20:17.718464Z"}, {"name": "execute", "started_at": "2021-12-31T19:20:17.718464Z", "completed_at": "2021-12-31T19:20:17.718464Z"}], "thread_id": "Thread-1", "execution_time": 0.0030002593994140625, "adapter_response": {}, "message": null, "failures": null, "unique_id": "test.sampledatastack.not_null_orders_order_id.cf6c17daed"}, {"status": "success", "timing": [{"name": "compile", "started_at": "2021-12-31T19:20:17.719465Z", "completed_at": "2021-12-31T19:20:17.722464Z"}, {"name": "execute", "started_at": "2021-12-31T19:20:17.723465Z", "completed_at": "2021-12-31T19:20:17.723465Z"}], "thread_id": "Thread-1", "execution_time": 0.0039997100830078125, "adapter_response": {}, "message": null, "failures": null, "unique_id": "test.sampledatastack.relationships_orders_customer_id__customer_id__ref_customers_.c6ec7f58f2"}, {"status": "success", "timing": [{"name": "compile", "started_at": "2021-12-31T19:20:17.723465Z", "completed_at": "2021-12-31T19:20:17.726464Z"}, {"name": "execute", "started_at": "2021-12-31T19:20:17.726464Z", "completed_at": "2021-12-31T19:20:17.726464Z"}], "thread_id": "Thread-1", "execution_time": 0.0029993057250976562, "adapter_response": {}, "message": null, "failures": null, "unique_id": "test.sampledatastack.unique_orders_order_id.fed79b3a6e"}], "elapsed_time": 1.4034347534179688, "args": {"write_json": true, "use_colors": true, "printer_width": 80, "version_check": true, "partial_parse": true, "static_parser": true, "profiles_dir": "C:\\Users\\Usuario\\.dbt", "send_anonymous_usage_stats": true, "event_buffer_size": 100000, "compile": true, "which": "generate", "rpc_method": "docs.generate", "indirect_selection": "eager"}}